itaxotools/__pyinstaller/hook-itaxotools.convphase_gui.py
itaxotools/convphase_gui/__init__.py
itaxotools/convphase_gui/config.py
itaxotools/convphase_gui/resources.py
itaxotools/convphase_gui/logos/convphase.ico
itaxotools/convphase_gui/logos/convphase.svg
itaxotools/convphase_gui/logos/convphase_cp.svg
itaxotools/convphase_gui/task/__init__.py
itaxotools/convphase_gui/task/input.py
itaxotools/convphase_gui/task/model.py
itaxotools/convphase_gui/task/process.py
itaxotools/convphase_gui/task/strings.py
itaxotools/convphase_gui/task/types.py
itaxotools/convphase_gui/task/view.py
itaxotools/convphase_gui/task/work.py
itaxotools_convphase_gui-0.2.0.dist-info/LICENSE.txt
itaxotools_convphase_gui-0.2.0.dist-info/METADATA
itaxotools_convphase_gui-0.2.0.dist-info/WHEEL
itaxotools_convphase_gui-0.2.0.dist-info/entry_points.txt
itaxotools_convphase_gui-0.2.0.dist-info/top_level.txt
itaxotools_convphase_gui-0.2.0.dist-info/RECORD
